pytranslations/__init__.py
pytranslations/translations.py
pytranslations-0.0.2.dist-info/LICENSE
pytranslations-0.0.2.dist-info/METADATA
pytranslations-0.0.2.dist-info/WHEEL
pytranslations-0.0.2.dist-info/top_level.txt
pytranslations-0.0.2.dist-info/RECORD
