Metadata-Version: 2.1
Name: pytranslations
Version: 0.0.2
Summary: Lightweight library for handling translations
Home-page: https://github.com/YLashko/translations/
Author: Wym
Author-email: dewreator2@gmail.com
License: MIT
Project-URL: Bug Tracker, https://github.com/YLashko/translations/issues/
Classifier: Programming Language :: Python :: 3
Classifier: License :: OSI Approved :: MIT License
Classifier: Operating System :: OS Independent
Requires-Python: >=3.6
License-File: LICENSE
